Metadata-Version: 2.1
Name: ohlcobject
Version: 1.0
Summary: Improve performance for handling OHLC against Pandas
Home-page: UNKNOWN
Author: OpenFibers
Author-email: openfibers@gmail.com
License: MIT
Platform: UNKNOWN
